torch_deploy/__init__.py
torch_deploy/app.py
torch_deploy/deploy.py
torch_deploy/logger.py
torch_deploy/processing.py
pytorch_deploy-0.0.6.dist-info/LICENSE
pytorch_deploy-0.0.6.dist-info/METADATA
pytorch_deploy-0.0.6.dist-info/WHEEL
pytorch_deploy-0.0.6.dist-info/top_level.txt
pytorch_deploy-0.0.6.dist-info/RECORD
