Metadata-Version: 2.1
Name: pytorch-deploy
Version: 0.0.6
Summary: Serving pytorch models on an API in one line.
Home-page: https://github.com/mochangheng/pytorch-deploy
Author: Owen Mo, Fiona Xie, Hulbert Zhang
Author-email: mochangheng@gmail.com, fionax@andrew.cmu.edu, hzeng012@ucr.edu
License: UNKNOWN
Platform: UNKNOWN
Classifier: Programming Language :: Python :: 3
Classifier: License :: OSI Approved :: MIT License
Classifier: Operating System :: OS Independent
Requires-Python: >=3.6
Requires-Dist: uvicorn
Requires-Dist: fastapi
Requires-Dist: pydantic
Requires-Dist: requests
Requires-Dist: jinja2
Requires-Dist: python-multipart
